htb/__init__.py
htb-1.1.0.dist-info/LICENSE
htb-1.1.0.dist-info/METADATA
htb-1.1.0.dist-info/WHEEL
htb-1.1.0.dist-info/top_level.txt
htb-1.1.0.dist-info/RECORD
